django_serve/__init__.py
django_serve/__main__.py
django_serve/apps.py
django_serve/main.py
django_serve/version.py
django_serve/management/__init__.py
django_serve/management/commands/__init__.py
django_serve/management/commands/serve.py
django_serve-0.3.dist-info/LICENSE
django_serve-0.3.dist-info/METADATA
django_serve-0.3.dist-info/WHEEL
django_serve-0.3.dist-info/entry_points.txt
django_serve-0.3.dist-info/top_level.txt
django_serve-0.3.dist-info/RECORD
