Metadata-Version: 2.1
Name: django-serve
Version: 0.3
Summary: A gunicorn based django runserver command.
Home-page: https://github.com/rsalmaso/django-serve
Download-URL: https://github.com/rsalmaso/django-serve/archive/main.zip
Author: Raffaele Salmaso
License: MIT License
Project-URL: Documentation, https://github.com/rsalmaso/django-serve/README.md
Project-URL: Source, https://github.com/rsalmaso/django-serve
Project-URL: Tracker, https://github.com/rsalmaso/django-serve/issues
Classifier: Development Status :: 5 - Production/Stable
Classifier: Intended Audience :: Developers
Classifier: Framework :: Django
Classifier: Framework :: Django :: 3.2
Classifier: Framework :: Django :: 4.0
Classifier: Framework :: Django :: 4.1
Classifier: Natural Language :: English
Classifier: License :: OSI Approved :: MIT License
Classifier: Programming Language :: Python
Classifier: Programming Language :: Python :: 3
Classifier: Programming Language :: Python :: 3.8
Classifier: Programming Language :: Python :: 3.9
Classifier: Programming Language :: Python :: 3.10
Classifier: Programming Language :: Python :: 3.11
Requires-Python: >=3.6
License-File: LICENSE
Requires-Dist: django
Requires-Dist: gunicorn
Requires-Dist: gunicorn-color
Requires-Dist: inotify ; sys_platform == "linux"
